republic/__init__.py
republic/prompt.py
republic-0.1.0.dist-info/METADATA
republic-0.1.0.dist-info/WHEEL
republic-0.1.0.dist-info/RECORD
