Metadata-Version: 2.4
Name: republic
Version: 0.1.0
Summary: The minimalistic AI stack for developers who value freedom and efficiency.
Author-email: Chojan Shang <psiace@apache.org>
Requires-Python: >=3.11
Provides-Extra: all
Requires-Dist: republic-prompt; extra == 'all'
Provides-Extra: prompt
Requires-Dist: republic-prompt; extra == 'prompt'
